mysqlgrantsdump/__init__.py
mysqlgrantsdump/main.py
mysqlgrantsdump-0.0.7.dist-info/LICENSE
mysqlgrantsdump-0.0.7.dist-info/METADATA
mysqlgrantsdump-0.0.7.dist-info/WHEEL
mysqlgrantsdump-0.0.7.dist-info/entry_points.txt
mysqlgrantsdump-0.0.7.dist-info/top_level.txt
mysqlgrantsdump-0.0.7.dist-info/RECORD
