Metadata-Version: 2.1
Name: mysqlgrantsdump
Version: 0.0.7
Summary: A Python package to fetch a list of all users and grants from a MariaDB database and output them in a human-readable table format to the console.
Home-page: https://lyuda.io
Author: lyuda io
Author-email: help@elyuda.io
License: UNKNOWN
Platform: UNKNOWN
Classifier: Programming Language :: Python :: 3
Classifier: License :: OSI Approved :: MIT License
Classifier: Operating System :: OS Independent
Requires-Python: >=3.7
License-File: LICENSE
Requires-Dist: mysql-connector-python (==8.0.32)
Requires-Dist: prettytable (==3.6.0)
